setup.py
shubhlipi/__init__.py
shubhlipi/crypted.py
shubhlipi/file.py
shubhlipi/git.py
shubhlipi/json.py
shubhlipi/kry.py
shubhlipi/lang_list.py
shubhlipi/min.py
shubhlipi/sign.py
shubhlipi/trans.py
shubhlipi.egg-info/PKG-INFO
shubhlipi.egg-info/SOURCES.txt
shubhlipi.egg-info/dependency_links.txt
shubhlipi.egg-info/requires.txt
shubhlipi.egg-info/top_level.txt