Metadata-Version: 2.1
Name: shubhlipi
Version: 0.0.0.182
Requires-Python: >=3.6
Requires-Dist: requests
Requires-Dist: pyperclip
Requires-Dist: rich
Requires-Dist: python-dotenv
